{
    "Buy":{
        "date":"Date and Time",
        "docType":"Transaction Type",
        "sbFee":"SB Fee",
        "wallet":"Asset",
        "newAssetBalance":"New Asset Balance",
        "state":"Status"
    },
    "Sell":{
        "date":"Date and Time",
        "docType":"Transaction Type",
        "sbFee":"SB Fee",
        "wallet":"Asset",
        "newAssetBalance":"New Asset Balance",
        "state":"Status"
    },
    "Deposit Crypto":{
        "docType":"Transaction Type",
        "date":"Date",
        "wallet":"Wallet",
        "Amount":["debit","credit"],
        "state":"State"
    },
    "Withdraw Crypto":{
        "docType":"Transaction Type",
        "date":"Date",
        "wallet":"Wallet",
        "Amount":["debit","credit"],
        "state":"State"
    },
    "Withdraw Fiat":{
        "docType":"Transaction Type",
        "date":"Date",
        "wallet":"Wallet",
        "Amount":["debit","credit"],
        "beneficiryName":"Sender/Recipient Full Name ",
        "accountnumber":"Bank Account Number/IBAN ",
        "state":"State"
    },
    "Deposit Fiat":{
        "docType":"Transaction Type",
        "transactionId":"Transaction Id",
        "date":"Date",
        "wallet":"Wallet",
        "Amount":["debit","credit"],
        "senderName":"Sender/Recipient Full Name ",
        "accountnumber":"Bank Account Number/IBAN ",
        "state":"State"
    }
}